{
  "data": [
    {
      "currencyTitle": "Us Dollar",
      "usd": 2.4512478,
      "code": "USD",
      "exchangeRate": 0.57912364
    },
    {
      "currencyTitle": "Afghanistan Afghani",
      "usd": 5.14761214,
      "code": "AFN",
      "exchangeRate": 1.05761432
    },
    {
      "currencyTitle": "United Arab Emirates Dirham",
      "usd": 12.02646581,
      "code": "AED",
      "exchangeRate": 0.15642465
    },
    {
      "currencyTitle": "European Union",
      "usd": 8.124712425,
      "code": "EUR",
      "exchangeRate": 0.187541231
    },
    {
      "currencyTitle": "Japanese",
      "usd": 10.78422121,
      "code": "JPY",
      "exchangeRate": 3.8425110221
    },
    {
      "currencyTitle": "Great Britain Pound",
      "usd": 7.1246121152,
      "code": "GBP",
      "exchangeRate": 0.25522648
    }
  ]
}
